turbocharge.py
turbocharge-0.0.2.dist-info/LICENSE.txt
turbocharge-0.0.2.dist-info/METADATA
turbocharge-0.0.2.dist-info/WHEEL
turbocharge-0.0.2.dist-info/entry_points.txt
turbocharge-0.0.2.dist-info/top_level.txt
turbocharge-0.0.2.dist-info/RECORD
