Metadata-Version: 2.1
Name: turbocharge
Version: 0.0.2
Summary: Turbocharged Way To Install All The Packages You Love!
Home-page: https://github.com/XtremeDevX/turbocharge
Author: xtremedevx
Author-email: xtremedevx@gmail.com
License: UNKNOWN
Platform: UNKNOWN
Classifier: License :: OSI Approved :: Apache Software License
Classifier: Operating System :: MacOS
Classifier: Operating System :: Microsoft :: Windows
Classifier: Operating System :: POSIX :: Linux
Requires-Dist: Click
Requires-Dist: progress
Requires-Dist: halo
